gammarers/aws_daily_cloud_watch_logs_archive_stack/__init__.py
gammarers/aws_daily_cloud_watch_logs_archive_stack/py.typed
gammarers/aws_daily_cloud_watch_logs_archive_stack/_jsii/__init__.py
gammarers/aws_daily_cloud_watch_logs_archive_stack/_jsii/aws-daily-cloud-watch-logs-archive-stack@2.9.30.jsii.tgz
gammarers_aws_daily_cloud_watch_logs_archive_stack-2.9.30.dist-info/LICENSE
gammarers_aws_daily_cloud_watch_logs_archive_stack-2.9.30.dist-info/METADATA
gammarers_aws_daily_cloud_watch_logs_archive_stack-2.9.30.dist-info/WHEEL
gammarers_aws_daily_cloud_watch_logs_archive_stack-2.9.30.dist-info/top_level.txt
gammarers_aws_daily_cloud_watch_logs_archive_stack-2.9.30.dist-info/RECORD
